{
  "id": "cabinet-5-2015",
  "type": "statute",
  "title": "قرار مجلس الوزراء رقم 5 لسنة 2015: في شأن رسوم الخدمات التي تقدمها مراكز التأشيرات في بعثات الدولة في الخارج",
  "title_en": "Cabinet Decision No. 5 of 2015",
  "short_name": "قرار مجلس الوزراء 5/2015",
  "status": "in_force",
  "issued_date": "2015-01-01",
  "in_force_date": "2015-01-01",
  "url": "https://elaws.moj.gov.ae/laws/ref/S-AL1_2_53927",
  "legal_zone": "federal",
  "language": "ar",
  "provisions": [
    {
      "provision_ref": "art2",
      "section": "2",
      "title": "–القراراتالتنفيذية*",
      "content": "منهذا القراربالوسائلالتي تقررهاوزارةالمالية.المادة4–القراراتالتنفيذية*يصدروزيرالخارجيةالقراراتاللازمةلتنفيذ أحكامهذا القراربعد التنسيقمع وزارةالمالية.المادة5–الغاءات*يلغىأي نص في أيقرار آخر الىالمدى الذييتعارض فيهوأحكام هذاالقرار.المادة6–النشروالنفاذ*ينشرهذا القرار فيالجريدةالرسمية،ويعمل به بعدثلاثين يومامن تاريخنشره.صدرعنا:\nبتاريخ:8ربيعالآخر1436هـ.\nالموافق:28يناير2015م.محمدبن راشد آلمكتومرئيسمجلسالوزراءنشرهذاالقرارفيعدد الجريدةالرسميةرقم576ص 47.",
      "language": "ar"
    }
  ],
  "definitions": []
}