{
  "id": "ministerial-36-1981",
  "type": "statute",
  "title": "قرار وزاري رقم 36/1 لسنة 1981: في شأن تحديد أوجه صرف الفروق المالية التي يعود نفعها على صاحب العمل من جراء الحرمان من الترقية أو الحرمان من العلاوة أو تأجيلها",
  "title_en": "Ministerial Decision No. 36 of 1981",
  "short_name": "قرار وزاري 36/1981",
  "status": "in_force",
  "issued_date": "1981-10-01",
  "in_force_date": "1981-10-01",
  "url": "https://elaws.moj.gov.ae/laws/ref/S-AL1_2_54961",
  "legal_zone": "federal",
  "language": "ar",
  "provisions": [
    {
      "provision_ref": "art108",
      "section": "108",
      "title": "فيشأن تنظيمعلاقاتالعمل.",
      "content": "من القانونالاتحادي رقم8/1980 تاريخ 20/4/1980م. فيشأن تنظيمعلاقاتالعمل.",
      "language": "ar"
    }
  ],
  "definitions": []
}