{
  "id": "ministerial-191-2009",
  "type": "statute",
  "title": "قرار وزاري رقم 191  لسنة 2009: في شأن تنظيم مرور الجمال عبر منافذ الدولة",
  "title_en": "Ministerial Decision No. 191 of 2009",
  "short_name": "قرار وزاري 191/2009",
  "status": "in_force",
  "issued_date": "2009-05-01",
  "in_force_date": "2009-05-01",
  "url": "https://elaws.moj.gov.ae/laws/ref/S-AL1_2_53100",
  "legal_zone": "federal",
  "language": "ar",
  "provisions": [
    {
      "provision_ref": "s1",
      "section": "1",
      "title": "قراروزاريرقم191لسنة 2009",
      "content": "قراروزاريرقم191لسنة 2009",
      "language": "ar"
    },
    {
      "provision_ref": "s2",
      "section": "2",
      "title": "صادربتاريخ10/05/2009م. لسنة",
      "content": "صادربتاريخ10/05/2009م. لسنة",
      "language": "ar"
    },
    {
      "provision_ref": "s3",
      "section": "3",
      "title": "الموافقفيه15جمادي الأولى1430هـ.",
      "content": "الموافقفيه15جمادي الأولى1430هـ.",
      "language": "ar"
    },
    {
      "provision_ref": "s4",
      "section": "4",
      "title": "فيشأن تنظيممرور الجمالعبر منافذالدولة",
      "content": "فيشأن تنظيممرور الجمالعبر منافذالدولة",
      "language": "ar"
    },
    {
      "provision_ref": "s5",
      "section": "5",
      "title": "بعدالاطلاع علىالقانونالاتحادي رقم(1) لسنة 1972م بشأناختصاصاتالوزاراتوصلاحياتالوز",
      "content": "بعدالاطلاع علىالقانونالاتحادي رقم(1) لسنة 1972م بشأناختصاصاتالوزاراتوصلاحياتالوزراءوالقوانينالمعدلة له.",
      "language": "ar"
    },
    {
      "provision_ref": "s6",
      "section": "6",
      "title": "وعلىالمرسومبقانوناتحادي رقم (1)لسنة 2006مبتعديل بعضاحكامالقانونالاتحاديرقم(1) لس",
      "content": "وعلىالمرسومبقانوناتحادي رقم (1)لسنة 2006مبتعديل بعضاحكامالقانونالاتحاديرقم(1) لسنة 1972م بشأناختصاصاتالوزاراتوصلاحياتالوزراءوتعديلاته.",
      "language": "ar"
    },
    {
      "provision_ref": "s7",
      "section": "7",
      "title": "وعلىالقانونالاتحادي رقم(6) لسنة 1979م فيشأن الحجرالبيطريوتعديلاته.",
      "content": "وعلىالقانونالاتحادي رقم(6) لسنة 1979م فيشأن الحجرالبيطريوتعديلاته.",
      "language": "ar"
    },
    {
      "provision_ref": "s8",
      "section": "8",
      "title": "وعلىقانون (نظام)رقم (1/57) لسنة 1999مفي شأن نظامالحجرالزراعيونظام الحجرالبيطري ل",
      "content": "وعلىقانون (نظام)رقم (1/57) لسنة 1999مفي شأن نظامالحجرالزراعيونظام الحجرالبيطري لدولمجلس التعاونلدول الخليجالعربية.",
      "language": "ar"
    },
    {
      "provision_ref": "s9",
      "section": "9",
      "title": "وعلىالقانونالاتحادي رقم(16) لسنة 2007م فيشأن الرفقبالحيوان.",
      "content": "وعلىالقانونالاتحادي رقم(16) لسنة 2007م فيشأن الرفقبالحيوان.",
      "language": "ar"
    },
    {
      "provision_ref": "s10",
      "section": "10",
      "title": "وعلىقرار مجلسالوزراء رقم (5)لسنة 2006م في شأنتخويلنا ببعضالمهامالوزارية.",
      "content": "وعلىقرار مجلسالوزراء رقم (5)لسنة 2006م في شأنتخويلنا ببعضالمهامالوزارية.",
      "language": "ar"
    },
    {
      "provision_ref": "s11",
      "section": "11",
      "title": "وعلىقرار مجلسالوزراء رقم (6)لسنة2009مفي شأن تنظيممرور الجمالعبر المنافذالحدوديةل",
      "content": "وعلىقرار مجلسالوزراء رقم (6)لسنة2009مفي شأن تنظيممرور الجمالعبر المنافذالحدوديةللدولة.",
      "language": "ar"
    },
    {
      "provision_ref": "s12",
      "section": "12",
      "title": "وعلىالقرارالوزاري رقم (460)لسنة 2001م بشأناللائحةالتنفيذيةلنظام الحجرالبيطري لدو",
      "content": "وعلىالقرارالوزاري رقم (460)لسنة 2001م بشأناللائحةالتنفيذيةلنظام الحجرالبيطري لدولمجلس التعاونلدول الخليجالعربية.",
      "language": "ar"
    },
    {
      "provision_ref": "s13",
      "section": "13",
      "title": "وعلىالقرارالوزاري رقم (384)لسنة 2008م بشأناللائحةالتنفيذيةللقانونالاتحادي رقم(16",
      "content": "وعلىالقرارالوزاري رقم (384)لسنة 2008م بشأناللائحةالتنفيذيةللقانونالاتحادي رقم(16) لسنة 2007م فيشأن الرفقبالحيوان.",
      "language": "ar"
    },
    {
      "provision_ref": "s14",
      "section": "14",
      "title": "وفيإطار حرصالوزارة علىتنفيذأهدافهاالإستراتيجيةفيما يتعلقبرفع معدلاتالأمن الحيويل",
      "content": "وفيإطار حرصالوزارة علىتنفيذأهدافهاالإستراتيجيةفيما يتعلقبرفع معدلاتالأمن الحيويلضمان سلامةالدولة منالمخاطرالبيولوجيةالناجمة عنالأوبئةوالامراضالتي تصيبالحيواناتوخاصةالمشتركة بينالإنسانوالحيوان.",
      "language": "ar"
    },
    {
      "provision_ref": "s15",
      "section": "15",
      "title": "وبناءعلى مقتضياتالمصلحةالعامة.",
      "content": "وبناءعلى مقتضياتالمصلحةالعامة.",
      "language": "ar"
    },
    {
      "provision_ref": "s16",
      "section": "16",
      "title": "يخضعدخول وخروجالجمال منوإلى الدولةلمواد وأحكامالقوانينواللوائحوالقراراتالمتعلقةب",
      "content": "يخضعدخول وخروجالجمال منوإلى الدولةلمواد وأحكامالقوانينواللوائحوالقراراتالمتعلقةبالثروةالحيوانيةوالمعمول بهافي الدولةولموادوأحكام هذاالقرار.",
      "language": "ar"
    },
    {
      "provision_ref": "s17",
      "section": "17",
      "title": "يجبأن تكونإرسالياتالجمال واردةمن دول ومناطقخالية منالامراضالتالية:",
      "content": "يجبأن تكونإرسالياتالجمال واردةمن دول ومناطقخالية منالامراضالتالية:",
      "language": "ar"
    },
    {
      "provision_ref": "s18",
      "section": "18",
      "title": "- (RVF) Rift valley fever",
      "content": "- (RVF) Rift valley fever",
      "language": "ar"
    },
    {
      "provision_ref": "s19",
      "section": "19",
      "title": "-حمي القرمالكونغوالنزفية",
      "content": "-حمي القرمالكونغوالنزفية",
      "language": "ar"
    },
    {
      "provision_ref": "s20",
      "section": "20",
      "title": "- Crimean Congo hemorrhagicfever (CCHF)",
      "content": "- Crimean Congo hemorrhagicfever (CCHF)",
      "language": "ar"
    },
    {
      "provision_ref": "s21",
      "section": "21",
      "title": "-داء البريمات(اللبتوسبيروزس)",
      "content": "-داء البريمات(اللبتوسبيروزس)",
      "language": "ar"
    },
    {
      "provision_ref": "s22",
      "section": "22",
      "title": "- Pseudo tuberculosisCorynebac-terium infection",
      "content": "- Pseudo tuberculosisCorynebac-terium infection",
      "language": "ar"
    },
    {
      "provision_ref": "s23",
      "section": "23",
      "title": "ويحقللادارةالمختصةبالوزارة رفعتقارير إليناتتعلق بإضافةأي امراضوبائية أخرىبعد درا",
      "content": "ويحقللادارةالمختصةبالوزارة رفعتقارير إليناتتعلق بإضافةأي امراضوبائية أخرىبعد دراسةوتقييم مخاطرالمرض.",
      "language": "ar"
    },
    {
      "provision_ref": "s24",
      "section": "24",
      "title": "يخضعدخول وخروجالجمال عبرمنافذ الدولةللشروطالتالية:",
      "content": "يخضعدخول وخروجالجمال عبرمنافذ الدولةللشروطالتالية:",
      "language": "ar"
    },
    {
      "provision_ref": "s25",
      "section": "25",
      "title": "أولا:الجمالالمستوردةبغرض التربيةوالذبحوسباقاتالهجنوالمزاينة:",
      "content": "أولا:الجمالالمستوردةبغرض التربيةوالذبحوسباقاتالهجنوالمزاينة:",
      "language": "ar"
    },
    {
      "provision_ref": "s26",
      "section": "26",
      "title": "1-الحصول علىإذن استيرادمسبق منالوزارةموضحا فيهالغرض منالاستيرادوبلد المنشأومنفذ ",
      "content": "1-الحصول علىإذن استيرادمسبق منالوزارةموضحا فيهالغرض منالاستيرادوبلد المنشأومنفذ الدخولكما يذكر منفذالخروج فيحالة مشاركةالجمال فيالسباقاتوالمزاينة.",
      "language": "ar"
    },
    {
      "provision_ref": "s27",
      "section": "27",
      "title": "2-أن تكونالإرساليةمصحوبةبشهادة صحيةبيطرية أصليةساريةالمفعولصادرة من جهةحكومية (ر",
      "content": "2-أن تكونالإرساليةمصحوبةبشهادة صحيةبيطرية أصليةساريةالمفعولصادرة من جهةحكومية (رسمية)من بلدالتصديروموثقة حسبالأصول، علىأن يذكر فيهابلد المنشأللجمال ورقمالشريحةالإلكترونيةوالعلاماتالمميزةللحيواناتوالتحصيناتالمعطاهللحيوانات.",
      "language": "ar"
    },
    {
      "provision_ref": "s28",
      "section": "28",
      "title": "3-أن تكونالإرساليةمصحوبةبشهادة منمختبر حكوميمعتمد، أويذكر فيالشهادةالصحية تأنالج",
      "content": "3-أن تكونالإرساليةمصحوبةبشهادة منمختبر حكوميمعتمد، أويذكر فيالشهادةالصحية تأنالجمال قد تماختبارهابفحوصاتمخبريةمعتمدة منالمنظماتالدولية ذاتالصلة، قبلمدة لا تزيد عن(30) يوما منتاريخالحصول،وكانت نتيجةالفحصالمعمليسالبة ضدالامراضالتالية:",
      "language": "ar"
    },
    {
      "provision_ref": "s29",
      "section": "29",
      "title": "-طفيليات الدمبما فيها(تريبانوسوماايفانزاي)",
      "content": "-طفيليات الدمبما فيها(تريبانوسوماايفانزاي)",
      "language": "ar"
    },
    {
      "provision_ref": "s30",
      "section": "30",
      "title": "Blood parasites including(Trypanosomiasis evansi)",
      "content": "Blood parasites including(Trypanosomiasis evansi)",
      "language": "ar"
    },
    {
      "provision_ref": "s31",
      "section": "31",
      "title": "4-أن تكونالجمال خاليةمن جميعالامراضالجلديةوالطفيلياتالخارجيةوالداخلية.",
      "content": "4-أن تكونالجمال خاليةمن جميعالامراضالجلديةوالطفيلياتالخارجيةوالداخلية.",
      "language": "ar"
    },
    {
      "provision_ref": "s32",
      "section": "32",
      "title": "5-في حالةاستيرادالجمال بغرضالتربية:",
      "content": "5-في حالةاستيرادالجمال بغرضالتربية:",
      "language": "ar"
    },
    {
      "provision_ref": "s33",
      "section": "33",
      "title": "أ-يتم حجرالحيوان لمدةلا تقل عن (21) يومفي البلدالمصدر قبلالشحنمباشرة،ويذكر ذلك ف",
      "content": "أ-يتم حجرالحيوان لمدةلا تقل عن (21) يومفي البلدالمصدر قبلالشحنمباشرة،ويذكر ذلك فيالشهادةالصحية.",
      "language": "ar"
    },
    {
      "provision_ref": "s34",
      "section": "34",
      "title": "ب–يتم حجرالجمال لمدةلا تقل عن (7)أيام في محجرمنفذ الدخولالمعتمد لعملالفحوصاتاللا",
      "content": "ب–يتم حجرالجمال لمدةلا تقل عن (7)أيام في محجرمنفذ الدخولالمعتمد لعملالفحوصاتاللازمةللتأكد منخلوها منالامراضالمعدية أوالوبائية.",
      "language": "ar"
    },
    {
      "provision_ref": "s35",
      "section": "35",
      "title": "6-في حالةاستيرادالجمال بغرضالذبح:",
      "content": "6-في حالةاستيرادالجمال بغرضالذبح:",
      "language": "ar"
    },
    {
      "provision_ref": "s36",
      "section": "36",
      "title": "أ-يجب أن تكونالجمال منالذكور.",
      "content": "أ-يجب أن تكونالجمال منالذكور.",
      "language": "ar"
    },
    {
      "provision_ref": "s37",
      "section": "37",
      "title": "ب-يتم حجرالجمال لمدةلا تقل عن (21) يومفي البلدالمصدر قبلالشحنمباشرة،ويذكر ذلك في",
      "content": "ب-يتم حجرالجمال لمدةلا تقل عن (21) يومفي البلدالمصدر قبلالشحنمباشرة،ويذكر ذلك فيالشهادةالصحية.",
      "language": "ar"
    },
    {
      "provision_ref": "s38",
      "section": "38",
      "title": "ج-يتم حجرالجمال لمدةلا تزيد عن (48)ساعة لحينإجراءالفحوصاتالمطلوبة.",
      "content": "ج-يتم حجرالجمال لمدةلا تزيد عن (48)ساعة لحينإجراءالفحوصاتالمطلوبة.",
      "language": "ar"
    },
    {
      "provision_ref": "s39",
      "section": "39",
      "title": "ثانيا-الجمالالعابرةبنظامالترانزيتعبر أراضيالدولة:",
      "content": "ثانيا-الجمالالعابرةبنظامالترانزيتعبر أراضيالدولة:",
      "language": "ar"
    },
    {
      "provision_ref": "s40",
      "section": "40",
      "title": "1-الحصول علىإذن استيرادمسبق منالدولةالمستوردة.",
      "content": "1-الحصول علىإذن استيرادمسبق منالدولةالمستوردة.",
      "language": "ar"
    },
    {
      "provision_ref": "s41",
      "section": "41",
      "title": "2-يصاحبالإرساليةالعابرةشهادة صحية فيالدولةالمصدرة.",
      "content": "2-يصاحبالإرساليةالعابرةشهادة صحية فيالدولةالمصدرة.",
      "language": "ar"
    },
    {
      "provision_ref": "s42",
      "section": "42",
      "title": "3-الحصول علىإذن عبور مسبقفي الوزارةيحدد فيهالمدة ومنفذالدخولوالخروج.",
      "content": "3-الحصول علىإذن عبور مسبقفي الوزارةيحدد فيهالمدة ومنفذالدخولوالخروج.",
      "language": "ar"
    },
    {
      "provision_ref": "s43",
      "section": "43",
      "title": "4-إصدار شهادةصحية من قبلطبيب الوزارةوالتأكد منأنها سليمةظاهرياوخالية من أيةامراض",
      "content": "4-إصدار شهادةصحية من قبلطبيب الوزارةوالتأكد منأنها سليمةظاهرياوخالية من أيةامراض وبائيةأو معديةوموضحا بهارقم الشريحةالإلكترونيةوالعلاماتالمميزةللحيوان.",
      "language": "ar"
    },
    {
      "provision_ref": "s44",
      "section": "44",
      "title": "5-ترصيص وسيلةالنقلالحاملةللجمالبواسطة سلطةالجماركبمنفذ الدخولوبحضورالطبيبالمسئول",
      "content": "5-ترصيص وسيلةالنقلالحاملةللجمالبواسطة سلطةالجماركبمنفذ الدخولوبحضورالطبيبالمسئول ولايحق التصرفبها حتىوصولها إلىمنفذ الخروج.",
      "language": "ar"
    },
    {
      "provision_ref": "s45",
      "section": "45",
      "title": "6-على الطبيبالمسئول فيمنفذ الخروجالتأكد منسلامةالترصيصوالأوراقالثبوتيةالمصاحبةلل",
      "content": "6-على الطبيبالمسئول فيمنفذ الخروجالتأكد منسلامةالترصيصوالأوراقالثبوتيةالمصاحبةللإرسالية.",
      "language": "ar"
    },
    {
      "provision_ref": "s46",
      "section": "46",
      "title": "7-لا يسمح بعبورالجمالالقادمة منالدولالمحظورالاستيرادمنها عبرأراضيالدولة.",
      "content": "7-لا يسمح بعبورالجمالالقادمة منالدولالمحظورالاستيرادمنها عبرأراضيالدولة.",
      "language": "ar"
    },
    {
      "provision_ref": "s47",
      "section": "47",
      "title": "ثالثا-خروجودخول الجمالعبر منافذالدولة بغرضالرعي:",
      "content": "ثالثا-خروجودخول الجمالعبر منافذالدولة بغرضالرعي:",
      "language": "ar"
    },
    {
      "provision_ref": "s48",
      "section": "48",
      "title": "1-أن تكونالجمالمملوكةلمواطني دولةالاماراتالعربيةالمتحدة.",
      "content": "1-أن تكونالجمالمملوكةلمواطني دولةالاماراتالعربيةالمتحدة.",
      "language": "ar"
    },
    {
      "provision_ref": "s49",
      "section": "49",
      "title": "2-عند خروجالجمال يتمفحصها من قبلطبيب الوزارةفي المنفذللتأكد منسلامتهاوإصدار شهاد",
      "content": "2-عند خروجالجمال يتمفحصها من قبلطبيب الوزارةفي المنفذللتأكد منسلامتهاوإصدار شهادةصحية لها.",
      "language": "ar"
    },
    {
      "provision_ref": "s50",
      "section": "50",
      "title": "3-تخضعإرسالياتالجمال عندعودتها منالرعيللإجراءاتالمحجريةالمعمول بهافي الدولة.",
      "content": "3-تخضعإرسالياتالجمال عندعودتها منالرعيللإجراءاتالمحجريةالمعمول بهافي الدولة.",
      "language": "ar"
    },
    {
      "provision_ref": "s51",
      "section": "51",
      "title": "رابعا:تصدير الجماللخارج الدولة:",
      "content": "رابعا:تصدير الجماللخارج الدولة:",
      "language": "ar"
    },
    {
      "provision_ref": "s52",
      "section": "52",
      "title": "1-الحصول علىإذن استيرادمسبق منالدولةالمستوردة.",
      "content": "1-الحصول علىإذن استيرادمسبق منالدولةالمستوردة.",
      "language": "ar"
    },
    {
      "provision_ref": "s53",
      "section": "53",
      "title": "2-الحصول علىشهادة منشأ أووثيقة مبايعةمصادق عليهارسميا من جهةالاختصاصبالدولةوموثق",
      "content": "2-الحصول علىشهادة منشأ أووثيقة مبايعةمصادق عليهارسميا من جهةالاختصاصبالدولةوموثقة حسبالأصولومذكورا بهارقم الشريحةالاليكترونيةالمعرفة لكلحيوانوالعلاماتالمميزةالأخرى.",
      "language": "ar"
    },
    {
      "provision_ref": "s54",
      "section": "54",
      "title": "3-الحصول علىشهادة صحيةبيطرية منطبيب الوزارةموضحا بها رقمالشريحةالالكترونيةوالعلا",
      "content": "3-الحصول علىشهادة صحيةبيطرية منطبيب الوزارةموضحا بها رقمالشريحةالالكترونيةوالعلاماتالمميزة.",
      "language": "ar"
    },
    {
      "provision_ref": "s55",
      "section": "55",
      "title": "4-أن تكون وسيلةالنقل مطابقةلشروط النقلالواردة فيقانون الرفقبالحيوانولائحتهالتنفي",
      "content": "4-أن تكون وسيلةالنقل مطابقةلشروط النقلالواردة فيقانون الرفقبالحيوانولائحتهالتنفيذية.",
      "language": "ar"
    },
    {
      "provision_ref": "s56",
      "section": "56",
      "title": "علىالادارةالمختصةبالوزارةالتنسيق معالجهات ذاتالعلاقةبالدولةلتنفيذ هذاالقرار.",
      "content": "علىالادارةالمختصةبالوزارةالتنسيق معالجهات ذاتالعلاقةبالدولةلتنفيذ هذاالقرار.",
      "language": "ar"
    },
    {
      "provision_ref": "s57",
      "section": "57",
      "title": "علىجميع الجهاتالمعنيةتنفيذ هذاالقرار كلفيما يخصه،ويعمل بهاعتبارا منتاريخ صدوره،و",
      "content": "علىجميع الجهاتالمعنيةتنفيذ هذاالقرار كلفيما يخصه،ويعمل بهاعتبارا منتاريخ صدوره،وينشر فيالجريدةالرسمية.",
      "language": "ar"
    },
    {
      "provision_ref": "s58",
      "section": "58",
      "title": "صدرفي:15جماديالأولى1430هـ\nالموافق:2009/5/10م",
      "content": "صدرفي:15جماديالأولى1430هـ\nالموافق:2009/5/10م",
      "language": "ar"
    },
    {
      "provision_ref": "s59",
      "section": "59",
      "title": "نشرهذاالقرارالوزاريفي عددالجريدةالرسمية رقم493ص 455.",
      "content": "نشرهذاالقرارالوزاريفي عددالجريدةالرسمية رقم493ص 455.",
      "language": "ar"
    }
  ],
  "definitions": []
}