{
  "id": "ministerial-764-2015",
  "type": "statute",
  "title": "قرار وزاري رقم 764 لسنة 2015: بشأن العمل بنماذج العقود المعتمدة من وزارة العمل",
  "title_en": "Ministerial Decision No. 764 of 2015",
  "short_name": "قرار وزاري 764/2015",
  "status": "in_force",
  "issued_date": "2015-09-01",
  "in_force_date": "2015-09-01",
  "url": "https://elaws.moj.gov.ae/laws/ref/S-AL1_2_55002",
  "legal_zone": "federal",
  "language": "ar",
  "provisions": [
    {
      "provision_ref": "art1",
      "section": "1",
      "title": "-النشروالنفاذ*",
      "content": "منهذا القرارإلا إذا كانتمتفقة معالأنظمةالقانونيةالمعمول بهافي الوزارة،وبشرط أن لاتتعارض معباقي نصوصالعقد، وبشرطموافقةالوزارة.المادة6 -النشروالنفاذ*يُنشرهذا القرار فيالجريدةالرسمية،ويُعمل به من1/1/2016.صدرعنا فيأبوظبي\nبتاريخ:27/9/2015 م.صقرغباشوزيرالعملنشرهذا القرارالوزاري فيعدد الجريدةالرسمية رقم 589ص 101.النموذجرقم (1) الخاصبعقد عملمُحدد المدةالمُرفقبقرار وزيرالعمل رقم (764)لسنة 2015رقمالعقد:...... (الرقمالتسلسلي لهكمعاملة فيالوزارة)إنهفي يوم ............الموافق ............. فيدولةالإمارات .......بين كلٍ من:1– منشأة(الاسم):رقمالمنشأة:الشكلالقانوني:العنوان/الإمارة...... المنطقة ......الشارع ...........الهاتفالأرضي:الهاتفالمحمول:صندوقالبريد:البريدالإلكتروني:الفاكس:ويمثلهاالاسم:رقمالجواز:الجنسية:الصفة:العنوان/الإمارة..... المنطقة ،....الشارع ......الهاتفالأرضي:الهاتفالمحمول:صندوقالبريد:البريدالإلكتروني:الفاكس:ويُشارإلى ما ذُكر فيهذا البند(بالطرف الأول)في عقد العملومُلحقه.2–السيد/السيدة-الاسم:-الجنسية:-رقم جوازالسفر:-ويُشار إلى ماذُكر في هذاالبند بالطرفالثاني أوالعامل/أوالعاملة فيعقد العملومُلحقه.-ويُشار إلى ماذُكر في هذينالبندين (1 و2)معاً(بالطرفين/أوالطرفان) فيعقد العملومُلحقه.تمهيد:حيثأبدى الطرفالأول رغبتهفي التعاقد معالطرف الثانيلتشغيله فيالعملالمُحددأدناه، لذلكوَقَّعالطرفانسابقاً عرضالعمل رقم (....)لسنة (......) وبعدأن أقر كلمنهمابأهليتهللتعاقد وبأنهذا التمهيد،وعرض العملالسابقتوقيعه منهماومُلحقه؛ جزءلا يتجزأ. منهذا العقدومُلحقه،لذلك اتفقالطرفان علىالآتي:البندالأوليلتزمالطرف الثانيبأن يعمل لدىالطرف الأولبوظيفة/أوبمهنة ..........،بدولةالإمارات/إمارة:......(ملاحظة:يُكتب هنامكان العمل).البند2تكونمدة هذا العقدعامين تبدأ منتاريخ دخولالدولة في .....(إذا كانالعاملمُستقدماً منخارجها لهذاالتعاقدتحديداً). ومنتاريخ تعديلوضعه في ...... (إذاكان العاملالمُتعاقدمعه داخلالدولة فعلاًلأسباب أخرىغير هذاالتعاقدتحديداً)وتنتهي مدةهذا العقد في .....البند3يعمل/(أولا يعمل) الطرفالثاني لدىالطرف الأولتحت التجربة،وتكون مدة هذهالتجربة (1 ... 2 ... 3 .. 4 .. 5 ....6 شهر)البند4فيحالة رغبةالطرفين فيتجديد هذاالعقد،يلتزمانبتوقيع نموذجتجديد عقدمُحدد المدة،ويتم ذلك قبلتاريخ انتهاءهذا العقد،ولا يبدأالطرفانالعمل بالعقدالمُجددإلَّا بعد أنيكون لدى كلمنهما نسخةمعتمدة منالعقد الجديدبعد اعتمادهامن الوزارة،ويتعين أن لايكون هناكفاصل زمني بينتاريخ انتهاءهذا العقدوبداية العملبالعقدالمُجدد.البند5تكونالراحةالأسبوعيةللطرف الثانيلمدة يومواحد/(أويومين)،ويلتزم الطرفالأول بتحديدهذه الأياموإعلام الطرفالثاني بها منتاريخ بدءعلاقة العمل.البند6اتفقالطرفان علىأن يعمل الطرفالثاني لدىالطرف الأولمقابل: أجرشهري مقداره..../أوأجر يوميمقداره..../أوأجر بالعمولة(بنسبة .....% منقيمةالأرباح/أوالمبيعات ......) أوأجر بالساعة(بقيمة ..... درهمإماراتي لكلساعة) أو أجربالقطعة(بقيمة ..... درهمإماراتي لكلوحدة)ويشملهذا الأجرالآتي:1-الأجرالأساسيومقداره ..........(ملاحظة: الأجريُكتببالأرقاموبالحروف،إذا كان العملمقابل الأجراليومي أوالشهري يجبوضع الأساسي،وإذا اختارالعمولة أوالساعة أوالقطعة تكونكتابةالأساسياختيارية)2-العلاوات: مثلالعلاوةالاجتماعية ........(إلخ من أيةعلاوات أخرى)3-البدلات(ملاحظة كلبَدل يُكتببالاسمويُكتبمقدارهبالأرقاموبالحروف أويكتب أمامه لايوجد في حالعدم وجوده، أويُكتب البديلالعيني لهذاالبدل مثلحالة منحالطرف الثانيسكناً فعلياًوليس بدلاًللسكن.)وتشملهذه البدلاتعلى سبيلالمثال الآتي:-بدل سكن .....-بدل انتقال .......-بدل طبيعة عمل.........-بدل تذكرة سفرله/وللأسرة.....-بدل غلاءمعيشة ........-بدل هاتف .........-بدل نقل أمتعة..........-بدل تدريسأبناء ...........-بدل نادي صحي..........-بدل مهام خارجالدولة .........-بدل تغذية ........-أية بدلاتأخرى ..........-ويكون التزامالطرف الأولبسداد الأجر،وقيام الطرفالثانيباستلام هذاالأجر، طبقاًللنظمالقانونيةالتي تقررهاالوزارة.--البند7علاقةالعمل، التيينظمها هذاالعقد، علاقةتعاقديةرضائية، ولايُلزم أي طرفمن الطرفينباستمرارتعاقده معالطرف الآخربغير إرادته،على أن يتحملالطرف الذيأنهى العلاقةبإرادتهالمنفردةكافة التبعاتالقانونيةالمترتبة علىذلك وفقاً لماهو مُحددبمُلحق هذاالعقد ووفقاًلأية أنظمةقانونية أخرىساريةبالوزارة.وتنتهي علاقةالعمل بينالطرفين إذاتوافرت حالةمن الحالاتالمنصوصعليها فيالبند (2) منبنود مُلحقهذا العقد.البند8يقرالطرف الأولبأنه أطْلَعالطرف الثانيتفصيلياً علىكافة البنودالواردة فيمُلحق هذاالعقد (سبعةبنود) كما يقربأن هذا العقدوملحقه مطابقلعرض العملومُلحقه،والذي سبقللطرف الثانيتوقيعه (ووضعبصمته عليهإذا كان منالمستوىالمهاريالرابع أوالخامس) فيدولةالاستقدام(إذا كانالعاملمستقدماً منخارج الدولة)أو داخلالدولة(بالنسبةللعمال الذينيتم تشغيلهممن داخلالدولة.)البند9يُقرالطرف الثانيبأنه اطَّلَعتفصيلياً علىكافة البنودالواردة فيمُلحق هذاالعقد (سبعةبنود) وعَلِمبكافة ماتضمَّنه منأحكام، كمايقر بأن هذاالعقد وملحقهمطابق لعرضالعملومُلحقه،والذي سبق أنقام بتوقيعه(ووضع بصمتهعليه إذا كانمن المستوىالمهاريالرابع أوالخامس) فيدولةالاستقدام(إذا كانالعاملمستقدماً منخارج الدولة)أو داخلالدولة(بالنسبةللعمال الذينيتم تشغيلهممن داخلالدولة.)البند10يُقرُّالطرفانبأنَّ كافةبنود مُلحقالعقد جزءٌ لايتجزأ منه،ومُكملة لهتماماً،ويلتزمانبكلِّ ما وردفيها.البند11اتفقالطرفان علىإضافة الشروطالآتية: 1 - ........ 2 - ...................3 - ......... إلخويجب– في هذهالحالة – أن لاتخالف الشروطالإضافيةالنظمالقانونيةالساريةبالوزارة، أوتخالف البنودالواردة فيهذا العقدوملحقه. وفيحالة إضافةهذه الشروطتتم إحالةالعقد للجهةالمختصةبعلاقاتالعملبالوزارةلمراجعتهاقبل إقرارها.البند12حُررهذا العقد منثلاث نسخ، بعدأن تمَّتوقيعه منالطرفين (ووضعالعامل بصمتهعليه في حالةالعامل منالمستوىالمهاريالرابع أوالخامس)،ويحتفظ كلمنهما بنسخة،والنسخةالثالثةمودعة لدىالوزارة.توقيعالطرف الأولتوقيعالطرف الثاني()()بصمةإبهام اليد ......للعامل من ذويالمستوىالمهاريالرابع أوالخامسملحوظة:ما هو مكتوببالأحرفالكبيرة معوجود خط تحتهمع وضعه بينالقوسين، هوللإيضاح فقطوليس جزءاً مننموذج هذاالعقد.مُلحقالنموذج رقم (1)الخاص بعقدالعمل مُحددالمدة رقم ()تمهيد:-في قراءة هذاالمُلحق، وفيقراءة عقدالعمل،المُشار إليهأعلاه، يُقصدبالكلماتوالعباراتالتالية،أينما وردتبهما، المعنىالمُبين قرينكل منها:الدولة:دولةالإماراتالعربيةالمتحدة.الوزارة:وزارة العمل.القانون:القانونالاتحادي رقم(8) لسنة 1980 في شأنتنظيم علاقاتالعمل، وأيةتعديلات تطرأعليه.النظمالقانونيةالسارية: هي –بالإضافةللقانونالمشار إليهأعلاه –مجموعةالقراراتالتنظيميةوالتعاميمالصادرةاستناداًللقانون،وتقومبتنفيذهاالوزارةبوصفهامجموعةالتشريعاتوالقواعدالحاكمةوالمُنظمةلسوق العملبالدولة.دولةالاستقدام:الدولةالقادم منهاالعامل، سواءكانت الدولةالتي ينتميإلى جنسيتها،أو أية دولةأخرى.عرضالعمل – (هذاالعرض): العرضالذي تمَّتقديمهللعامل في بلدالاستقدام،أو الذي تمتقديمه لهداخل الدولة،ووقعه العاملوبَصم عليهإذا منالمستوىالمهاريالرابع أوالخامس،والذي بناءعليه تمَّتوقيع عقدالعمل،ويرتبط بهذاالعرضارتباطاًكاملاًالمُلحقالخاص به.العقد(هذا العقد/عقدالعمل): عقدالعمل المشارإليه أعلاه،الذي تمَّإبرامه بناءعلى العرضالذي تمتقديمهللعامل ووقععليه.الطرفالأول: صاحبالعمل.الطرفالثاني:العامل أوالعاملة.الطرفان:صاحب العملوالعامل.الأجر(الأجرالإجمالي): هوكل ما يُعطىللطرف الثانيلقاء عمله،بموجب عقدالعمل سواءكان نقداً أوعيناً، بما فيذلك من بدلاتأو علاوة غلاءمعيشة أو أيةبدلات أوعلاوات أخرى.الأجرالأساسي: هوالأجر الذيينص عليه عقدالعمل أثناءسريانه بينالطرفين ولاتدخل ضمن هذاالأجرالبدلات أياًكان نوعها.تعديلالوضع: هوتحويل إذندخول الدولةأياً ما يكونإلى إذن دخولللعمل.إصابةالعمل: هيإصابة الطرفالثاني بأحدالأمراضالمهنيةالمبينةبالجدولالملحقبالقانون، أوبأية إصابةأخرى ناشئة عنعمله حصلت لهأثناء تأديةذلك العملوبسببه،ويُعتبر فيحكم إصابةالعمل كل حادثيقع للطرفالثاني خلالفترة ذهابهإلى عمله أوعودته منهبشرط أن يكونالذهابوالإياب دونتوقف أو تخلفأو انحراف عنالطريقالطبيعي.وحيثأبدى الطرفالأول رغبتهفي التعاقد معالطرف الثانيللقيامبالعملالمُحدد فيالبند (الأول)من عقد العمل،لذا فقد قامالطرفانبتوقيع العقدالمشار إليهأعلاه، وتمإرفاق هذاالملحقبالعقد، حيثاطلع الطرفانتفصيلياً علىكافة البنودالواردةفيهما،وعَلِمابكافة ماتضمَّنته تلكالبنود منأحكام،وتتمثل هذهالبنود فيالآتيالبند1إذااجتاز الطرفالثاني بنجاحفترةالتجربة،المُحددة فيالبند الثالثمن عقد العمل،واستمر فيالعمل يتماحتساب تلكالفترة ضمنمدة خدمتهالكلية.وللطرف الأولالاستغناء عنخدمات الطرفالثاني خلالفترة التجربةدون إنذارودون مكافأةنهاية الخدمة.البند2علاقةالعمل، التيينظمها هذاالعقد، علاقةتعاقديةرضائية، ولايُلزَم أي طرفمن الطرفينباستمرارتعاقده معالطرف الآخربغير إرادته،على أن يتحملالطرف الذييُنهيالعلاقةبإرادتهالمنفردةكافة التبعاتالقانونيةالمترتبة علىذلك وفقاً لماهو مُحدد بهذاالمُلحقووفقاًللأنظمةالقانونيةالسارية.وتنتهي علاقةالعمل بينالطرفين إذاتوافرت حالةمن الحالاتالآتية:1-إذا انتهت مدةالعقدالمُتفقعليها بينالطرفين، ولميتم تجديد هذاالعقد طبقاًللبند الرابعمن عقد العمل.2-إذا اتفقالطرفان علىإنهاء العقدأثناءسريانه، بشرطأن تكونموافقةالعاملمكتوبة.3-في حال قيامأحد الطرفينمنفرداًبإنهاءالعقد، وبدونأن يكون الطرفالآخر سبباًفي الإنهاء،وفي هذهالحالة يتحملالطرف الذيأنهى العقدبإرادتهالمنفردةتبعات هذاالإنهاء،ومنها ما هومنصوص عليه فيالمواد (115 و116 و128)من قانونتنظيم علاقاتالعملالمُشار إليه.4– في حال قيامصاحب العملبإنهاء علاقةالعمل لسبب منالأسبابالواردةبالفقرات من (1إلى 9) من البند (4)من هذا الملحق.1-5-حالة ثبوتإخلال صاحبالعملبالتزاماتهالمقررةقانوناً أواتفاقاً (علىسبيل المثاللا الحصر حالةالاعتداء علىالعامل من طرفصاحب العمل أومِمن يمثله)6-حالاتاستحالةالتنفيذ بسببيرجع للطرفالثاني(الوفاة،العجز الكلي،المرض، بلوغسن التقاعد) أوبسبب يرجعللطرف الأول(إغلاقالمنشأةبالإغلاقالإداري أوالإغلاق غيرالإداري بأمرمن المحكمة أومن السلطاتالمختصة) أوبسبب الظروفالقاهرة.7-في حال قيامالطرف الأولبإنهاءالعلاقةالتعاقديةلسبب لا يمتللعمل بصلة،وبوجه خاص إذاكان إنهاءالعلاقة بسببتقدم الطرفالثاني بشكوىجدية إلىالجهاتالمختصة أوإقامة دعوىعلى الطرفالأول ثبتصحتها وفقاًللمادة 122 منقانون تنظيمعلاقات العمل.البند3 -التزاماتالطرف الأول(صاحب العمل)لغاياتتنفيذ عقدالعمل بينالطرفين،يلتزم الطرفالأول بالآتي:1-تمكين الطرفالثاني منأداء العملالمتفق عليهمن تاريخ دخولالدولة في..../أوومن تاريختعديل وضعه في......، وإنهاء أيةإجراءاتتفرضها النظمالقانونيةالرسميةلمباشرة هذاالعمل، وأنْيُمكن الطرفالثاني منتوقيع عقدالعمل قبلمباشرة العملخلال أسبوعينمن تواريخالتمكين منالعملالمُبينةبهذه الفقرة.2-استخراج نسخةمن عقد العملمن الوزارة،ويقومبالتوقيععليه مع الطرفالثاني،وتقديمه إلىالوزارةلاعتمادهخلال المددالتي تقررهاالوزارة،وتسليم نسخةمن هذا العقدالمعتمدللطرفالثاني، معنسخة من تصريحالعمل.3-أن يُسددللطرف الثانيالأجرالمُستحق،وأن يؤدي إليهأية حقوق أومزايا أخرى،طبقاً لما هومنصوص عليه فيعقد العمل،ووفقاًللمواعيدوالإجراءاتوالنظمالقانونيةالسارية فيالوزارة، ولايجوز لهاقتطاع أيمبلغ من أجرالطرفالثاني، لقاءحقوق خاصة،إلّا فيالحالاتالآتية:-أ-استردادالسلف أوالمبالغ التيدُفعت إلىالطرف الثانيزيادة على حقهبشرط ألايجاوز مايُقتطع منالأجر في هذهالحالة عشرةفي المائة منالأجر الدوريللعامل.ب-الأقساط التييجب قانوناًعلى الطرفالثاني دفعهامن أجرهكأنظمةالضمانالاجتماعيوالتأمينات.ج-اشتراكاتالطرف الثانيفي صندوقالادخار أوالسلفالمستحقةللصندوق إذاوُجد.د-أقساط أيمشروعاجتماعي أوأية مزايا أوخدمات أخرىيقدمها الطرفالأول وتوافقعليهاالوزارة.ه-الغراماتالتي تُوقععلى الطرفالثاني بسببالمخالفاتالتي يرتكبها.و-كل دَينيُستوفي لحكمقضائي على ألايزيد مايُقتطعتنفيذاًللحكم على ربعالأجرالمستحقللطرفالثاني، وإذاتعددت الديونأو تعددالدائنوناعتبر حدهاالأعلى نصفالأجر،وتُقسمالمبالغالمطلوبحجزها بينمستحقيهاقسمة غرماءبعد دفع دينالنفقةالشرعيةبنسبة ربعالأجر.4-أن يزود الطرفالثانيبمواعيدالعمل،ومواعيدالراحاتالأسبوعيةواليومية مععقد العمل،كما يجب عليهأنْ يضعها فيأماكن العملالتي تحددهاالنظمالقانونيةالسارية.5– أن يتحرىالدقة تماماًفي تقديم أيةشكوى أواخطارات تخصالطرفالثاني، بمافي ذلك بلاغالانقطاعالمفاجئ عنالعمل دونإتباعالإجراءاتالقانونية،وإذا ثبت عدمالجدية فيماتقدم به يكونللوزارةاتخاذ ما تنصعليه النظمالقانونيةالسارية بهافي حقه.6– أن لا يُلزمالطرف الثانيبشراء أغذيةأو سلع من محالمعينة أو مماينتجه الطرفالأول.7– مع مراعاة ماورد بالفقرة (4)من هذا البند،على الطرفالأول أن لايقوم بتشغيلالطرف الثانيفي اليومالواحد أكثرمن 8 ساعات، أوأكثر من 48 ساعةفي الأسبوع،ويستثنى منذلك ما يأتي:أولاً:حالات تخفيضساعات العمل:أ-تخفيض ساعاتالعملاليوميةبالنسبة إلىالأعمالالمرهقةوالضارةبالصحة كمايحددهاالوزيرب-تخفيض ساعاتالعملاليوميةبمقدارساعتين خلالشهر رمضان.ثانياً:حالات زيادةساعات العمل:أ-زيادة ساعاتالعمل إلى تسعساعات فياليوم فيالأعمالالتجاريةوأعمالالفنادقوالمقاصفوالحراسةوغيرها منالأعمال التييجوز إضافتهابقرار منالوزير بشرطالالتزامبالآتي:- أن يتمالإنقاص منساعات العملالعادية فيأحد أيامالعملالأسبوعيةبمقدارالزيادة على 8ساعات فيالأيامالأخرى بحيثلا يتجاوز عددإجمالي ساعاتالعمل فيالأسبوع 48ساعة. ويجوزالعمل بنظامالمناوباتالذي تزيدفيها ساعاتالعملاليوميةالعادية على 9ساعات، بشرطأن لا يتجاوزمجموع ساعاتالعملالأسبوعية 48ساعة. وأن تحددمواعيد العملفي كل نوبةويُخطر بهاالطرف الثانيوتوضع علىالأبوابالرئيسيةللمنشأةوتخطر بهاالوزارة.ب-زيادة ساعاتالعمل إلىساعتينإضافيتين فقطفي اليومالواحد،ويجوز زيادةساعات العملإلى أكثر منساعتينإضافيتين إذاكان العمللازماً لمنعوقوع خسارةجسيمة أو حادثخطير. ويلتزمالطرف الأولبأن يدفعللطرف الثانيعن ساعاتالعملالإضافية،المنصوصعلي",
      "language": "ar"
    }
  ],
  "definitions": []
}