{
  "id": "ministerial-119-2007",
  "type": "statute",
  "title": "قرار وزاري رقم 119 لسنة 2007: العمل المؤقت",
  "title_en": "Ministerial Decision No. 119 of 2007",
  "short_name": "قرار وزاري 119/2007",
  "status": "in_force",
  "issued_date": "2007-02-01",
  "in_force_date": "2007-02-01",
  "url": "https://elaws.moj.gov.ae/laws/ref/S-AL1_2_54923",
  "legal_zone": "federal",
  "language": "ar",
  "provisions": [
    {
      "provision_ref": "s1",
      "section": "1",
      "title": "قراروزاريرقم119 لسنة 2007",
      "content": "قراروزاريرقم119 لسنة 2007",
      "language": "ar"
    },
    {
      "provision_ref": "s2",
      "section": "2",
      "title": "صادربتاريخ25/02/2007م. لسنة",
      "content": "صادربتاريخ25/02/2007م. لسنة",
      "language": "ar"
    },
    {
      "provision_ref": "s3",
      "section": "3",
      "title": "الموافقفيه 8 صفر 1428ﻫ.",
      "content": "الموافقفيه 8 صفر 1428ﻫ.",
      "language": "ar"
    },
    {
      "provision_ref": "s4",
      "section": "4",
      "title": "بعدالاطلاع علىالقانونالاتحادي رقم 1لسنة 1972م.والقوانينالمعدلة فيشأن اختصاصاتالو",
      "content": "بعدالاطلاع علىالقانونالاتحادي رقم 1لسنة 1972م.والقوانينالمعدلة فيشأن اختصاصاتالوزاراتوصلاحياتالوزراء.",
      "language": "ar"
    },
    {
      "provision_ref": "s5",
      "section": "5",
      "title": "وعلىالمرسومالاتحادي رقم 8لسنة1980م.والقوانينالمعدلة له فيشأن تنظيمعلاقاتالعمل.",
      "content": "وعلىالمرسومالاتحادي رقم 8لسنة1980م.والقوانينالمعدلة له فيشأن تنظيمعلاقاتالعمل.",
      "language": "ar"
    },
    {
      "provision_ref": "s6",
      "section": "6",
      "title": "وعلىقرار مجلسالوزراء رقم 19لسنة 2005م. في شأننظام الرسوموالضمانالمصرفي.",
      "content": "وعلىقرار مجلسالوزراء رقم 19لسنة 2005م. في شأننظام الرسوموالضمانالمصرفي.",
      "language": "ar"
    },
    {
      "provision_ref": "s7",
      "section": "7",
      "title": "وعلىقرار مجلسالوزراء رقم 18لسنة2005م.فيشأن نقلالكفالةواعارةالمكفولينوالرسومالمقر",
      "content": "وعلىقرار مجلسالوزراء رقم 18لسنة2005م.فيشأن نقلالكفالةواعارةالمكفولينوالرسومالمقررةلذلك.",
      "language": "ar"
    },
    {
      "provision_ref": "s8",
      "section": "8",
      "title": "وعلىالقرارالوزاري رقم 401لسنة1997م.فيشأن تنظيمالعمل المؤقتوالعمل لبعضالوقت فيمنش",
      "content": "وعلىالقرارالوزاري رقم 401لسنة1997م.فيشأن تنظيمالعمل المؤقتوالعمل لبعضالوقت فيمنشآت القطاعالخاصبالدولة.",
      "language": "ar"
    },
    {
      "provision_ref": "s9",
      "section": "9",
      "title": "وعلىما عرضه وكيلالوزارة.",
      "content": "وعلىما عرضه وكيلالوزارة.",
      "language": "ar"
    },
    {
      "provision_ref": "s10",
      "section": "10",
      "title": "فيتطبيق احكامهذا القراريقصد بالعملالمؤقت كل عملتقتضي طبيعةتنفيذه اوانجازه مدةمحد",
      "content": "فيتطبيق احكامهذا القراريقصد بالعملالمؤقت كل عملتقتضي طبيعةتنفيذه اوانجازه مدةمحددة لا تزيدعن ستة اشهر.",
      "language": "ar"
    },
    {
      "provision_ref": "s11",
      "section": "11",
      "title": "تصريحالعمل المؤقتيعطى مرتينلكل فترةتعاقدية معصاحب العمل (لاتقل عن ثلاثسنوات) لجم",
      "content": "تصريحالعمل المؤقتيعطى مرتينلكل فترةتعاقدية معصاحب العمل (لاتقل عن ثلاثسنوات) لجميعالمهن، شريطةتوفير الشروطالتالية:",
      "language": "ar"
    },
    {
      "provision_ref": "s12",
      "section": "12",
      "title": "1-ان تكونللعامل اقامةعمل ساريةالمفعول الىتاريخ انتهاءمدة التصريحالمؤقت.",
      "content": "1-ان تكونللعامل اقامةعمل ساريةالمفعول الىتاريخ انتهاءمدة التصريحالمؤقت.",
      "language": "ar"
    },
    {
      "provision_ref": "s13",
      "section": "13",
      "title": "2-ان يكونالعامل قدامضى مدة سنةعلى الاقل فيالخدمة لدىصاحب العمل(الكفيل).",
      "content": "2-ان يكونالعامل قدامضى مدة سنةعلى الاقل فيالخدمة لدىصاحب العمل(الكفيل).",
      "language": "ar"
    },
    {
      "provision_ref": "s14",
      "section": "14",
      "title": "3-ان يقدم مايثبتالموافقةالخطية منصاحب العمل(الكفيل).",
      "content": "3-ان يقدم مايثبتالموافقةالخطية منصاحب العمل(الكفيل).",
      "language": "ar"
    },
    {
      "provision_ref": "s15",
      "section": "15",
      "title": "4-ان يقدم طلبالتصريحالمؤقت وفقاللقواعدوالاجراءاتالمتبعة بعدسداد الرسومالمقررةلذل",
      "content": "4-ان يقدم طلبالتصريحالمؤقت وفقاللقواعدوالاجراءاتالمتبعة بعدسداد الرسومالمقررةلذلك.",
      "language": "ar"
    },
    {
      "provision_ref": "s16",
      "section": "16",
      "title": "يكونصاحب العمل(الكفيل)مسؤولا عنالوفاء بجميعالالتزاماتالمستحقةللعامل وفقالشروط ال",
      "content": "يكونصاحب العمل(الكفيل)مسؤولا عنالوفاء بجميعالالتزاماتالمستحقةللعامل وفقالشروط العقدواحكامالقانون كمايكون مسؤولاعن مراعاةصلاحية اقامةالعاملوتصريح عملهوالرسوموالغراماتالمرتبطةبذلك.",
      "language": "ar"
    },
    {
      "provision_ref": "s17",
      "section": "17",
      "title": "استثناءمن حكمالفقرتين (2) و(3)من المادةالثانيةاعلاه يجوزللوزارة ودونالرجوع لصاحب",
      "content": "استثناءمن حكمالفقرتين (2) و(3)من المادةالثانيةاعلاه يجوزللوزارة ودونالرجوع لصاحبالعمل منحتصريح عملمؤقت للعاملفي الاحوالالاتية:",
      "language": "ar"
    },
    {
      "provision_ref": "s18",
      "section": "18",
      "title": "1-اذا كان لدىالعامل قضيةعمالية محالةمن الوزارةللمحكمة.",
      "content": "1-اذا كان لدىالعامل قضيةعمالية محالةمن الوزارةللمحكمة.",
      "language": "ar"
    },
    {
      "provision_ref": "s19",
      "section": "19",
      "title": "2-اذا لم يقمصاحب العملبدفع اجورالعامل لمدةشهرين بناءعلى تقريرمكتوب منادارة تفتيش",
      "content": "2-اذا لم يقمصاحب العملبدفع اجورالعامل لمدةشهرين بناءعلى تقريرمكتوب منادارة تفتيشالعمل اوادارة علاقاتالعملبالوزارة.",
      "language": "ar"
    },
    {
      "provision_ref": "s20",
      "section": "20",
      "title": "ويصدرالتصريح فيالحالتينالمذكورتيناعلاهبموافقة مديرادارة علاقاتالعمل او مديرمكتب ",
      "content": "ويصدرالتصريح فيالحالتينالمذكورتيناعلاهبموافقة مديرادارة علاقاتالعمل او مديرمكتب العملالمختص.",
      "language": "ar"
    },
    {
      "provision_ref": "s21",
      "section": "21",
      "title": "يجوزلوكيلالوزارة اووكيل الوزارةالمساعداستثناء ايحالات اخرى مناحكام هذاالقرار وعل",
      "content": "يجوزلوكيلالوزارة اووكيل الوزارةالمساعداستثناء ايحالات اخرى مناحكام هذاالقرار وعلىوكيل الوزارةوضع النماذجواصدارالتوجيهاتاللازمةلتطبيق احكامهذا القرار،ويعرض اي طلبللعمل لبعضالوقت علىمكتب الوزيرللنظر فيه حسبظروف كل حالةعلى حده.",
      "language": "ar"
    },
    {
      "provision_ref": "s22",
      "section": "22",
      "title": "يلغىالقرارانالوزاريانرقم (401) و(402) لسنة1997.",
      "content": "يلغىالقرارانالوزاريانرقم (401) و(402) لسنة1997.",
      "language": "ar"
    },
    {
      "provision_ref": "s23",
      "section": "23",
      "title": "يعملبهذا القراراعتبارا منتاريخ 22/2/2007م.وينشر فيالجريدةالرسمية.",
      "content": "يعملبهذا القراراعتبارا منتاريخ 22/2/2007م.وينشر فيالجريدةالرسمية.",
      "language": "ar"
    },
    {
      "provision_ref": "s24",
      "section": "24",
      "title": "التاريخ:8 صفر1428ﻫ.\nالموافق:25 /2/2007م.",
      "content": "التاريخ:8 صفر1428ﻫ.\nالموافق:25 /2/2007م.",
      "language": "ar"
    },
    {
      "provision_ref": "s25",
      "section": "25",
      "title": "نشرهذا القرارالوزاري فيعددي الجريدةالرسمية رقم 464و466 ص 113و223.",
      "content": "نشرهذا القرارالوزاري فيعددي الجريدةالرسمية رقم 464و466 ص 113و223.",
      "language": "ar"
    }
  ],
  "definitions": []
}